language_pipes/__init__.py
language_pipes/cli.py
language_pipes/config.py
language_pipes/lp.py
language_pipes/network_protocol.py
language_pipes/oai_server.py
language_pipes/test_cli.py
language_pipes/commands/edit.py
language_pipes/commands/initialize.py
language_pipes/commands/start.py
language_pipes/commands/upgrade.py
language_pipes/commands/view.py
language_pipes/distributed_state_network/__init__.py
language_pipes/distributed_state_network/dsnode.py
language_pipes/distributed_state_network/handler.py
language_pipes/distributed_state_network/objects/config.py
language_pipes/distributed_state_network/objects/data_packet.py
language_pipes/distributed_state_network/objects/endpoint.py
language_pipes/distributed_state_network/objects/hello_packet.py
language_pipes/distributed_state_network/objects/msg_types.py
language_pipes/distributed_state_network/objects/peers_packet.py
language_pipes/distributed_state_network/objects/signed_packet.py
language_pipes/distributed_state_network/objects/state_packet.py
language_pipes/distributed_state_network/util/__init__.py
language_pipes/distributed_state_network/util/aes.py
language_pipes/distributed_state_network/util/byte_helper.py
language_pipes/distributed_state_network/util/ecdsa.py
language_pipes/distributed_state_network/util/key_manager.py
language_pipes/jobs/job.py
language_pipes/jobs/job_data.py
language_pipes/jobs/job_factory.py
language_pipes/jobs/job_processor.py
language_pipes/jobs/job_receiver.py
language_pipes/jobs/job_time.py
language_pipes/jobs/job_tracker.py
language_pipes/jobs/network_job.py
language_pipes/jobs/timing_stats.py
language_pipes/llm_layer_collector/__init__.py
language_pipes/llm_layer_collector/cache.py
language_pipes/llm_layer_collector/compute.py
language_pipes/llm_layer_collector/helpers.py
language_pipes/llm_layer_collector/layer_collector.py
language_pipes/llm_layer_collector/load_layer.py
language_pipes/llm_layer_collector/state_obj.py
language_pipes/llm_layer_collector/auto/auto_layer.py
language_pipes-0.19.7.dist-info/METADATA
language_pipes-0.19.7.dist-info/WHEEL
language_pipes-0.19.7.dist-info/entry_points.txt
language_pipes-0.19.7.dist-info/licenses/LICENSE
language_pipes-0.19.7.dist-info/RECORD
