Metadata-Version: 2.4
Name: language-pipes
Version: 0.19.7
Summary: A privacy focused distributed algorithm for llm inference
Project-URL: Homepage, https://github.com/erinclemmer/language-pipes
Project-URL: Issues, https://github.com/erinclemmer/language-pipes/issues
Author-email: Erin Clemmer <erin.c.clemmer@gmail.com>
License-Expression: MIT
License-File: LICENSE
Keywords: AI,Language Model,distributed,networking,pipe,pipeline,server
Classifier: Development Status :: 4 - Beta
Classifier: Intended Audience :: Science/Research
Classifier: License :: OSI Approved :: MIT License
Classifier: Operating System :: OS Independent
Classifier: Programming Language :: Python :: 3.10
Classifier: Topic :: Scientific/Engineering :: Artificial Intelligence
Classifier: Typing :: Typed
Requires-Python: >=3.10
Requires-Dist: cryptography
Requires-Dist: ecdsa
Requires-Dist: flask
Requires-Dist: logging
Requires-Dist: promise
Requires-Dist: requests
Requires-Dist: toml
Requires-Dist: torch
Requires-Dist: transformers==4.57.6
Requires-Dist: uuid
